dictoo/__init__.py
dictoo/dicty.py
dictoo/op.py
dictoo-1.0.dist-info/LICENSE
dictoo-1.0.dist-info/METADATA
dictoo-1.0.dist-info/WHEEL
dictoo-1.0.dist-info/top_level.txt
dictoo-1.0.dist-info/RECORD
