Metadata-Version: 2.1
Name: dictoo
Version: 1.0
Summary: Utilities for working with json-style datastructures.
Home-page: https://github.com/7Z0nE/dicty
Author: Frederik Wegner
Author-email: onlyknoppas@gmail.com
Requires-Python: >=3.7
License-File: LICENSE
